infractl/__init__.py
infractl/api/__init__.py
infractl/api/deploy.py
infractl/api/infrastructure.py
infractl/api/program.py
infractl/api/run.py
infractl/api/runtime.py
infractl/base/__init__.py
infractl/base/infrastructure.py
infractl/base/program.py
infractl/base/registry.py
infractl/base/runtime.py
infractl/base/settings.py
infractl/cli/__init__.py
infractl/cli/main.py
infractl/docker/__init__.py
infractl/docker/builder.py
infractl/docker/local.py
infractl/docker/remote.py
infractl/docker/prefect/__init__.py
infractl/docker/prefect/builder.py
infractl/hub/__init__.py
infractl/hub/config.py
infractl/hub/jupyterhub.py
infractl/hub/kube.py
infractl/hub/main.py
infractl/hub/rest.py
infractl/hub/root.py
infractl/hub/server.py
infractl/logging/__init__.py
infractl/logging/logging.py
infractl/plugins/__init__.py
infractl/plugins/icl_infrastructure/__init__.py
infractl/plugins/icl_infrastructure/infrastructure.py
infractl/plugins/prefect_runtime/__init__.py
infractl/plugins/prefect_runtime/program.py
infractl/plugins/prefect_runtime/runtime.py
infractl/plugins/prefect_runtime/utils.py
infractl/prefect/__init__.py
infractl/prefect/engine.py
infractl/prefect/wrapper.py
infractl-0.0.3.dist-info/LICENSE
infractl-0.0.3.dist-info/METADATA
infractl-0.0.3.dist-info/WHEEL
infractl-0.0.3.dist-info/entry_points.txt
infractl-0.0.3.dist-info/top_level.txt
infractl-0.0.3.dist-info/RECORD
