Metadata-Version: 2.1
Name: infractl
Version: 0.0.3
Summary: API driven Machine Learning suite
Author-email: Areg Melik-Adamyan <areg.melikadamyan@gmail.com>, Pavel Chekin <pbchekin@gmail.com>
License: Apache License
Project-URL: Homepage, https://intel-ai.github.io/icl
Project-URL: Source, https://github.com/intel-ai/icl
Classifier: Development Status :: 3 - Alpha
Classifier: Environment :: GPU
Classifier: Framework :: Jupyter :: JupyterLab
Classifier: License :: OSI Approved :: Apache Software License
Classifier: Programming Language :: Python :: 3
Classifier: Operating System :: OS Independent
Requires-Python: >=3.8
License-File: LICENSE
Requires-Dist: boto3
Requires-Dist: click
Requires-Dist: docker
Requires-Dist: dynaconf
Requires-Dist: fsspec >=2023.9.2
Requires-Dist: pydantic <2.0.0
Requires-Dist: python-docker
Requires-Dist: s3fs >=2023.9.2
Requires-Dist: prefect ==2.13.0
Requires-Dist: kubernetes
Requires-Dist: anyio <4.0.0,>=3.4.0
Requires-Dist: asyncio
Provides-Extra: build
Requires-Dist: build ; extra == 'build'
Requires-Dist: twine ; extra == 'build'
Provides-Extra: integration_tests
Requires-Dist: minio ; extra == 'integration_tests'
Requires-Dist: pytest ; extra == 'integration_tests'
Requires-Dist: pytest-asyncio ; extra == 'integration_tests'
Requires-Dist: pytest-depends ==1.0.1 ; extra == 'integration_tests'
Requires-Dist: pytest-xdist ; extra == 'integration_tests'
Requires-Dist: ray ==2.6.1 ; extra == 'integration_tests'
Provides-Extra: unit_tests
Requires-Dist: build ; extra == 'unit_tests'
Requires-Dist: pytest ; extra == 'unit_tests'
Requires-Dist: pytest-asyncio ; extra == 'unit_tests'
Requires-Dist: pre-commit ; extra == 'unit_tests'
Requires-Dist: coverage ; extra == 'unit_tests'
